pylambert.so
pylambert-1.0.data/headers/lambert.h
pylambert-1.0.dist-info/DESCRIPTION.rst
pylambert-1.0.dist-info/METADATA
pylambert-1.0.dist-info/RECORD
pylambert-1.0.dist-info/WHEEL
pylambert-1.0.dist-info/metadata.json
pylambert-1.0.dist-info/top_level.txt
