Metadata-Version: 2.0
Name: pylambert
Version: 1.0
Summary: A Python wrapper to the C lambert library
Home-page: https://github.com/yageek/lambert-python
Author: Yannick Heinrich
Author-email: yannick.heinrich@gmail.com
License: UNKNOWN
Keywords: lambert,coordinates,gps,wgs84
Platform: UNKNOWN
